[
  {
    "constant": false,
    "inputs": [
      {
        "internalType": "address",
        "name": "_sender",
        "type": "address"
      },
      {
        "internalType": "uint256",
        "name": "_cardId",
        "type": "uint256"
      },
      {
        "internalType": "uint256",
        "name": "_etherValue",
        "type": "uint256"
      }
    ],
    "name": "_initiateSellingOffer",
    "outputs": [],
    "payable": false,
    "stateMutability": "nonpayable",
    "type": "function"
  },
  {
    "constant": false,
    "inputs": [
      {
        "internalType": "address",
        "name": "_sender",
        "type": "address"
      },
      {
        "internalType": "uint256",
        "name": "_tradeCard",
        "type": "uint256"
      },
      {
        "internalType": "uint256",
        "name": "_forCard",
        "type": "uint256"
      }
    ],
    "name": "_initiateTradingOffer",
    "outputs": [],
    "payable": false,
    "stateMutability": "nonpayable",
    "type": "function"
  },
  {
    "constant": false,
    "inputs": [
      {
        "internalType": "address",
        "name": "contractaddress",
        "type": "address"
      },
      {
        "internalType": "address",
        "name": "_from",
        "type": "address"
      },
      {
        "internalType": "address",
        "name": "_to",
        "type": "address"
      },
      {
        "internalType": "uint256",
        "name": "_CardId",
        "type": "uint256"
      }
    ],
    "name": "_transfer",
    "outputs": [],
    "payable": false,
    "stateMutability": "nonpayable",
    "type": "function"
  },
  {
    "constant": false,
    "inputs": [
      {
        "internalType": "uint256",
        "name": "_offerNumber",
        "type": "uint256"
      }
    ],
    "name": "acceptSellingOffer",
    "outputs": [
      {
        "internalType": "bool",
        "name": "",
        "type": "bool"
      }
    ],
    "payable": true,
    "stateMutability": "payable",
    "type": "function"
  },
  {
    "constant": false,
    "inputs": [
      {
        "internalType": "uint256",
        "name": "_offerNumber",
        "type": "uint256"
      }
    ],
    "name": "acceptTradingOffer",
    "outputs": [],
    "payable": false,
    "stateMutability": "nonpayable",
    "type": "function"
  },
  {
    "constant": false,
    "inputs": [
      {
        "internalType": "uint256",
        "name": "_newPrice",
        "type": "uint256"
      }
    ],
    "name": "changePackCost",
    "outputs": [],
    "payable": false,
    "stateMutability": "nonpayable",
    "type": "function"
  },
  {
    "constant": false,
    "inputs": [
      {
        "internalType": "uint256",
        "name": "_auctionTime",
        "type": "uint256"
      },
      {
        "internalType": "uint8",
        "name": "timeFormat",
        "type": "uint8"
      },
      {
        "internalType": "address",
        "name": "_owner",
        "type": "address"
      },
      {
        "internalType": "uint256",
        "name": "_CardId",
        "type": "uint256"
      },
      {
        "internalType": "uint256",
        "name": "_TokenId",
        "type": "uint256"
      }
    ],
    "name": "createAuctionContract",
    "outputs": [],
    "payable": false,
    "stateMutability": "nonpayable",
    "type": "function"
  },
  {
    "anonymous": false,
    "inputs": [
      {
        "indexed": true,
        "internalType": "address",
        "name": "previousOwner",
        "type": "address"
      },
      {
        "indexed": true,
        "internalType": "address",
        "name": "newOwner",
        "type": "address"
      }
    ],
    "name": "OwnershipTransferred",
    "type": "event"
  },
  {
    "constant": false,
    "inputs": [
      {
        "internalType": "uint256",
        "name": "_packNumber",
        "type": "uint256"
      }
    ],
    "name": "purchasePack",
    "outputs": [],
    "payable": true,
    "stateMutability": "payable",
    "type": "function"
  },
  {
    "constant": false,
    "inputs": [],
    "name": "renounceOwnership",
    "outputs": [],
    "payable": false,
    "stateMutability": "nonpayable",
    "type": "function"
  },
  {
    "anonymous": false,
    "inputs": [
      {
        "indexed": false,
        "internalType": "address",
        "name": "_from",
        "type": "address"
      },
      {
        "indexed": false,
        "internalType": "address",
        "name": "_to",
        "type": "address"
      },
      {
        "indexed": false,
        "internalType": "uint256",
        "name": "_tokenId",
        "type": "uint256"
      }
    ],
    "name": "Transfer",
    "type": "event"
  },
  {
    "constant": false,
    "inputs": [
      {
        "internalType": "uint256",
        "name": "_cardId",
        "type": "uint256"
      },
      {
        "internalType": "address",
        "name": "_to",
        "type": "address"
      }
    ],
    "name": "transferACardToFriend",
    "outputs": [],
    "payable": false,
    "stateMutability": "nonpayable",
    "type": "function"
  },
  {
    "constant": false,
    "inputs": [
      {
        "internalType": "address",
        "name": "newOwner",
        "type": "address"
      }
    ],
    "name": "transferOwnership",
    "outputs": [],
    "payable": false,
    "stateMutability": "nonpayable",
    "type": "function"
  },
  {
    "constant": true,
    "inputs": [
      {
        "internalType": "uint256",
        "name": "",
        "type": "uint256"
      }
    ],
    "name": "cards",
    "outputs": [
      {
        "internalType": "uint256",
        "name": "tokenid",
        "type": "uint256"
      },
      {
        "internalType": "uint256",
        "name": "cardid",
        "type": "uint256"
      }
    ],
    "payable": false,
    "stateMutability": "view",
    "type": "function"
  },
  {
    "constant": true,
    "inputs": [],
    "name": "cardsOnAuction",
    "outputs": [
      {
        "internalType": "uint256[]",
        "name": "",
        "type": "uint256[]"
      }
    ],
    "payable": false,
    "stateMutability": "view",
    "type": "function"
  },
  {
    "constant": true,
    "inputs": [
      {
        "internalType": "address",
        "name": "_owner",
        "type": "address"
      }
    ],
    "name": "getCardsByOwner",
    "outputs": [
      {
        "internalType": "uint256[]",
        "name": "",
        "type": "uint256[]"
      }
    ],
    "payable": false,
    "stateMutability": "view",
    "type": "function"
  },
  {
    "constant": true,
    "inputs": [],
    "name": "getContractBalance",
    "outputs": [
      {
        "internalType": "uint256",
        "name": "",
        "type": "uint256"
      }
    ],
    "payable": false,
    "stateMutability": "view",
    "type": "function"
  },
  {
    "constant": true,
    "inputs": [],
    "name": "giveMeAddresses",
    "outputs": [
      {
        "internalType": "address[]",
        "name": "",
        "type": "address[]"
      }
    ],
    "payable": false,
    "stateMutability": "view",
    "type": "function"
  },
  {
    "constant": true,
    "inputs": [],
    "name": "isOwner",
    "outputs": [
      {
        "internalType": "bool",
        "name": "",
        "type": "bool"
      }
    ],
    "payable": false,
    "stateMutability": "view",
    "type": "function"
  },
  {
    "constant": true,
    "inputs": [],
    "name": "owner",
    "outputs": [
      {
        "internalType": "address",
        "name": "",
        "type": "address"
      }
    ],
    "payable": false,
    "stateMutability": "view",
    "type": "function"
  },
  {
    "constant": true,
    "inputs": [],
    "name": "sellingOffers",
    "outputs": [
      {
        "internalType": "uint256[]",
        "name": "",
        "type": "uint256[]"
      },
      {
        "internalType": "uint256[]",
        "name": "",
        "type": "uint256[]"
      },
      {
        "internalType": "uint256[]",
        "name": "",
        "type": "uint256[]"
      }
    ],
    "payable": false,
    "stateMutability": "view",
    "type": "function"
  },
  {
    "constant": true,
    "inputs": [],
    "name": "TradingOffers",
    "outputs": [
      {
        "internalType": "uint256[]",
        "name": "",
        "type": "uint256[]"
      },
      {
        "internalType": "uint256[]",
        "name": "",
        "type": "uint256[]"
      },
      {
        "internalType": "uint256[]",
        "name": "",
        "type": "uint256[]"
      }
    ],
    "payable": false,
    "stateMutability": "view",
    "type": "function"
  }
]